xheap.py
xheap-0.17.dist-info/DESCRIPTION.rst
xheap-0.17.dist-info/METADATA
xheap-0.17.dist-info/RECORD
xheap-0.17.dist-info/WHEEL
xheap-0.17.dist-info/metadata.json
xheap-0.17.dist-info/top_level.txt
