Metadata-Version: 2.0
Name: xheap
Version: 0.17
Summary: Heap Implementation for Python
Home-page: https://github.com/srkunze/xheap
Author: Sven R. Kunze
Author-email: srkunze@mail.de
License: MIT
Platform: UNKNOWN
Classifier: Development Status :: 2 - Pre-Alpha
Classifier: Intended Audience :: Developers
Classifier: License :: OSI Approved :: MIT License
Classifier: Programming Language :: Python
